google/transliteration/__init__.py
google/transliteration/numerals.py
google/transliteration/transliterate.py
google_transliteration_api-1.0.3.dist-info/METADATA
google_transliteration_api-1.0.3.dist-info/WHEEL
google_transliteration_api-1.0.3.dist-info/top_level.txt
google_transliteration_api-1.0.3.dist-info/RECORD
