Metadata-Version: 2.1
Name: google-transliteration-api
Version: 1.0.3
Summary: Google Transliterate API for Python
Home-page: UNKNOWN
License: MIT
Project-URL: Documentation, https://narvidhai.github.io/Google-Transliterate-API
Project-URL: Tracker, https://github.com/NarVidhai/Google-Transliterate-API/issues
Project-URL: Source, https://github.com/NarVidhai/Google-Transliterate-API
Keywords: Google Transliterate API - Google Input Tools Transliteration
Platform: UNKNOWN
Classifier: Programming Language :: Python :: 3
Classifier: License :: OSI Approved :: Apache Software License
Classifier: Operating System :: OS Independent
Classifier: Topic :: Scientific/Engineering :: Artificial Intelligence
Classifier: Topic :: Software Development :: Libraries
